odoo/addons/l10n_es_facturae/README.rst
odoo/addons/l10n_es_facturae/__init__.py
odoo/addons/l10n_es_facturae/__manifest__.py
odoo/addons/l10n_es_facturae/hooks.py
odoo/addons/l10n_es_facturae/data/Facturaev3_2.xsd
odoo/addons/l10n_es_facturae/data/Facturaev3_2_1.xsd
odoo/addons/l10n_es_facturae/data/Facturaev3_2_2.xsd
odoo/addons/l10n_es_facturae/data/xmldsig-core-schema.xsd
odoo/addons/l10n_es_facturae/data/template/account.tax-es_canary_common.csv
odoo/addons/l10n_es_facturae/data/template/account.tax-es_common_mainland.csv
odoo/addons/l10n_es_facturae/i18n/bg.po
odoo/addons/l10n_es_facturae/i18n/ca.po
odoo/addons/l10n_es_facturae/i18n/cs.po
odoo/addons/l10n_es_facturae/i18n/de.po
odoo/addons/l10n_es_facturae/i18n/es.po
odoo/addons/l10n_es_facturae/i18n/es_CO.po
odoo/addons/l10n_es_facturae/i18n/es_CR.po
odoo/addons/l10n_es_facturae/i18n/eu.po
odoo/addons/l10n_es_facturae/i18n/fr.po
odoo/addons/l10n_es_facturae/i18n/gl.po
odoo/addons/l10n_es_facturae/i18n/hr.po
odoo/addons/l10n_es_facturae/i18n/l10n_es_facturae.pot
odoo/addons/l10n_es_facturae/i18n/nl.po
odoo/addons/l10n_es_facturae/i18n/pl.po
odoo/addons/l10n_es_facturae/i18n/pt.po
odoo/addons/l10n_es_facturae/i18n/pt_BR.po
odoo/addons/l10n_es_facturae/i18n/ru.po
odoo/addons/l10n_es_facturae/i18n/sl.po
odoo/addons/l10n_es_facturae/i18n/sv.po
odoo/addons/l10n_es_facturae/i18n/tr.po
odoo/addons/l10n_es_facturae/i18n/vi.po
odoo/addons/l10n_es_facturae/models/__init__.py
odoo/addons/l10n_es_facturae/models/account_chart_template.py
odoo/addons/l10n_es_facturae/models/account_move.py
odoo/addons/l10n_es_facturae/models/account_tax.py
odoo/addons/l10n_es_facturae/models/l10n_es_facturae_attachment.py
odoo/addons/l10n_es_facturae/models/payment_mode.py
odoo/addons/l10n_es_facturae/models/res_company.py
odoo/addons/l10n_es_facturae/models/res_currency.py
odoo/addons/l10n_es_facturae/models/res_partner.py
odoo/addons/l10n_es_facturae/readme/CONFIGURE.md
odoo/addons/l10n_es_facturae/readme/CONTEXT.md
odoo_addon_l10n_es_facturae-18.0.1.1.0.dist-info/METADATA
odoo_addon_l10n_es_facturae-18.0.1.1.0.dist-info/WHEEL
odoo_addon_l10n_es_facturae-18.0.1.1.0.dist-info/top_level.txt
odoo_addon_l10n_es_facturae-18.0.1.1.0.dist-info/RECORD
