Metadata-Version: 2.1
Name: odoo-addon-l10n_es_facturae
Version: 18.0.1.1.0
Requires-Python: >=3.10
Requires-Dist: odoo-addon-account_payment_partner==18.0.*
Requires-Dist: odoo-addon-base_iso3166==18.0.*
Requires-Dist: odoo-addon-l10n_es_aeat==18.0.*
Requires-Dist: odoo-addon-l10n_es_partner==18.0.*
Requires-Dist: odoo-addon-report_qweb_parameter==18.0.*
Requires-Dist: odoo-addon-report_xml==18.0.*
Requires-Dist: odoo==18.0.*
Requires-Dist: pycountry
Requires-Dist: xmlsig
Summary: =?utf-8?q?Creaci=C3=B3n_de_Facturae?=
Home-page: https://github.com/OCA/l10n-spain
License: AGPL-3
Author: ASR-OSS, FactorLibre, Tecon, Comunitea, Tecnativa, Dixmit, Odoo Community Association (OCA)
Author-email: support@odoo-community.org
Classifier: Programming Language :: Python
Classifier: Framework :: Odoo
Classifier: Framework :: Odoo :: 18.0
Classifier: License :: OSI Approved :: GNU Affero General Public License v3
